{"CMSParallelRemarkEnabled":{"gc_runs":[{"PSYoungGen":{"from":"11288","to":"3318","total":"36864","time":null},"info":{"from":"11288","to":"3326","total":"119808","gctime":"0.0022040","user":"0.01","sys":"0.00","real":"0.00"}},{"PSYoungGen":{"from":"3318","to":"0","total":"36864","time":null},"ParOldGen":{"from":"8","to":"3145","total":"82944","time":null},"PSPermGen":{"from":"5076","to":"5074","total":"21504","time":null},"info":{"gctime":"0.0109740","from":"3326","to":"3145","total":"119808","user":"0.04","sys":"0.00","real":"0.01"}},{"PSYoungGen":{"from":"0","to":"0","total":"36864","time":null},"info":{"from":"3145","to":"3145","total":"119808","gctime":"0.0002900","user":"0.00","sys":"0.00","real":"0.00"}},{"PSYoungGen":{"from":"0","to":"0","total":"36864","time":null},"ParOldGen":{"from":"3145","to":"3145","total":"82944","time":null},"PSPermGen":{"from":"5074","to":"5074","total":"21504","time":null},"info":{"gctime":"0.0040430","from":"3145","to":"3145","total":"119808","user":"0.02","sys":"0.00","real":"0.01"}},{"PSYoungGen":{"from":"31744","to":"4496","total":"36864","time":null},"info":{"from":"34889","to":"7641","total":"119808","gctime":"0.0012150","user":"0.01","sys":"0.00","real":"0.00"}},{"PSYoungGen":{"from":"36240","to":"4464","total":"36864","time":null},"info":{"from":"39385","to":"7609","total":"119808","gctime":"0.0009180","user":"0.00","sys":"0.00","real":"0.01"}},{"PSYoungGen":{"from":"36208","to":"4464","total":"36864","time":null},"info":{"from":"39353","to":"7609","total":"119808","gctime":"0.0014650","user":"0.01","sys":"0.00","real":"0.00"}},{"PSYoungGen":{"from":"36197","to":"4496","total":"36864","time":null},"info":{"from":"39343","to":"7641","total":"119808","gctime":"0.0013080","user":"0.01","sys":"0.00","real":"0.00"}},{"PSYoungGen":{"from":"36240","to":"4544","total":"36352","time":null},"info":{"from":"39385","to":"7689","total":"119296","gctime":"0.0012480","user":"0.01","sys":"0.00","real":"0.00"}},{"PSYoungGen":{"from":"35776","to":"4560","total":"37376","time":null},"info":{"from":"38921","to":"7705","total":"120320","gctime":"0.0012150","user":"0.01","sys":"0.00","real":"0.00"}},{"PSYoungGen":{"from":"35271","to":"4512","total":"34816","time":null},"info":{"from":"38417","to":"7761","total":"117760","gctime":"0.0013450","user":"0.01","sys":"0.00","real":"0.00"}},{"PSYoungGen":{"from":"34716","to":"480","total":"36864","time":null},"info":{"from":"37966","to":"7841","total":"119808","gctime":"0.0010180","user":"0.01","sys":"0.00","real":"0.00"}},{"PSYoungGen":{"from":"30176","to":"416","total":"29696","time":null},"info":{"from":"37537","to":"7857","total":"112640","gctime":"0.0006650","user":"0.00","sys":"0.00","real":"0.00"}},{"PSYoungGen":{"from":"29600","to":"6233","total":"36352","time":null},"info":{"from":"37041","to":"13810","total":"119296","gctime":"0.0033460","user":"0.02","sys":"0.00","real":"0.00"}},{"PSYoungGen":{"from":"34905","to":"1732","total":"30208","time":null},"info":{"from":"42482","to":"12905","total":"113152","gctime":"0.0027540","user":"0.02","sys":"0.00","real":"0.01"}}],"heap":{"PSYoungGen ":{"total":"30208","used":"4641","eden space ":{"size":"28160","percent":"10"},"from space ":{"size":"2048","percent":"84"},"to   space ":{"size":"8192","percent":"0"}},"ParOldGen ":{"total":"82944","used":"11173","object space ":{"size":"82944","percent":"13"}},"PSPermGen ":{"total":"21504","used":"12910","object space ":{"size":"21504","percent":"60"}}},"stats":{"DefNew_count":0,"PSYoungGen_count":15,"PSOldGen_count":0,"PSPermGen_count":2}},"UseCMSInitiatingOccupancyOnly":{"gc_runs":[{"PSYoungGen":{"from":"11288","to":"3313","total":"36864","time":null},"info":{"from":"11288","to":"3321","total":"119808","gctime":"0.0023670","user":"0.01","sys":"0.00","real":"0.00"}},{"PSYoungGen":{"from":"3313","to":"0","total":"36864","time":null},"ParOldGen":{"from":"8","to":"3145","total":"82944","time":null},"PSPermGen":{"from":"5076","to":"5074","total":"21504","time":null},"info":{"gctime":"0.0112640","from":"3321","to":"3145","total":"119808","user":"0.04","sys":"0.00","real":"0.01"}},{"PSYoungGen":{"from":"0","to":"0","total":"36864","time":null},"info":{"from":"3145","to":"3145","total":"119808","gctime":"0.0003730","user":"0.00","sys":"0.00","real":"0.00"}},{"PSYoungGen":{"from":"0","to":"0","total":"36864","time":null},"ParOldGen":{"from":"3145","to":"3145","total":"82944","time":null},"PSPermGen":{"from":"5074","to":"5074","total":"21504","time":null},"info":{"gctime":"0.0043720","from":"3145","to":"3145","total":"119808","user":"0.02","sys":"0.00","real":"0.01"}},{"PSYoungGen":{"from":"31744","to":"4464","total":"36864","time":null},"info":{"from":"34889","to":"7609","total":"119808","gctime":"0.0011860","user":"0.01","sys":"0.00","real":"0.00"}},{"PSYoungGen":{"from":"36208","to":"4544","total":"36864","time":null},"info":{"from":"39353","to":"7689","total":"119808","gctime":"0.0009460","user":"0.01","sys":"0.00","real":"0.00"}},{"PSYoungGen":{"from":"36288","to":"4512","total":"36864","time":null},"info":{"from":"39433","to":"7657","total":"119808","gctime":"0.0011720","user":"0.01","sys":"0.00","real":"0.00"}},{"PSYoungGen":{"from":"36256","to":"4480","total":"36864","time":null},"info":{"from":"39401","to":"7625","total":"119808","gctime":"0.0013440","user":"0.00","sys":"0.00","real":"0.00"}},{"PSYoungGen":{"from":"36220","to":"4496","total":"36352","time":null},"info":{"from":"39365","to":"7641","total":"119296","gctime":"0.0015300","user":"0.01","sys":"0.00","real":"0.00"}},{"PSYoungGen":{"from":"35723","to":"4560","total":"37376","time":null},"info":{"from":"38869","to":"7705","total":"120320","gctime":"0.0011860","user":"0.00","sys":"0.00","real":"0.00"}},{"PSYoungGen":{"from":"35280","to":"4464","total":"34816","time":null},"info":{"from":"38425","to":"7705","total":"117760","gctime":"0.0013140","user":"0.01","sys":"0.00","real":"0.00"}},{"PSYoungGen":{"from":"34672","to":"480","total":"36864","time":null},"info":{"from":"37913","to":"7817","total":"119808","gctime":"0.0012080","user":"0.00","sys":"0.01","real":"0.01"}},{"PSYoungGen":{"from":"30176","to":"464","total":"29696","time":null},"info":{"from":"37513","to":"7873","total":"112640","gctime":"0.0008470","user":"0.01","sys":"0.00","real":"0.00"}},{"PSYoungGen":{"from":"29648","to":"6175","total":"36352","time":null},"info":{"from":"37057","to":"13712","total":"119296","gctime":"0.0041250","user":"0.03","sys":"0.00","real":"0.00"}},{"PSYoungGen":{"from":"34847","to":"1553","total":"30208","time":null},"info":{"from":"42384","to":"12666","total":"113152","gctime":"0.0027760","user":"0.02","sys":"0.00","real":"0.00"}}],"heap":{"PSYoungGen ":{"total":"30208","used":"4651","eden space ":{"size":"28160","percent":"11"},"from space ":{"size":"2048","percent":"75"},"to   space ":{"size":"8192","percent":"0"}},"ParOldGen ":{"total":"82944","used":"11113","object space ":{"size":"82944","percent":"13"}},"PSPermGen ":{"total":"21504","used":"12911","object space ":{"size":"21504","percent":"60"}}},"stats":{"DefNew_count":0,"PSYoungGen_count":15,"PSOldGen_count":0,"PSPermGen_count":2}},"UseConcMarkSweepGC":{"gc_runs":[{"CMS":{"from":"0","to":"3177","total":"83392","time":null},"info":{"gctime":"0.0144230","from":"11098","to":"3177","total":"120896","user":"0.01","sys":"0.00","real":"0.02"}},{"CMS":{"from":"3177","to":"3177","total":"83392","time":null},"info":{"gctime":"0.0082510","from":"3177","to":"3177","total":"120960","user":"0.01","sys":"0.00","real":"0.01"}},{"ParNew":{"from":"33408","to":"4159","total":"37568","time":null},"info":{"from":"36585","to":"7431","total":"120960","gctime":"0.0011930","user":"0.01","sys":"0.00","real":"0.00"}},{"ParNew":{"from":"37567","to":"306","total":"37568","time":null},"info":{"from":"40839","to":"7510","total":"120960","gctime":"0.0011350","user":"0.00","sys":"0.01","real":"0.00"}},{"ParNew":{"from":"33714","to":"107","total":"37568","time":null},"info":{"from":"40918","to":"7311","total":"120960","gctime":"0.0006450","user":"0.00","sys":"0.00","real":"0.00"}},{"ParNew":{"from":"33515","to":"4159","total":"37568","time":null},"info":{"from":"40719","to":"11476","total":"120960","gctime":"0.0010580","user":"0.00","sys":"0.00","real":"0.00"}},{"ParNew":{"from":"37567","to":"271","total":"37568","time":null},"info":{"from":"44884","to":"11521","total":"120960","gctime":"0.0012170","user":"0.01","sys":"0.00","real":"0.00"}},{"ParNew":{"from":"33679","to":"295","total":"37568","time":null},"info":{"from":"44929","to":"11545","total":"120960","gctime":"0.0005550","user":"0.00","sys":"0.00","real":"0.00"}},{"ParNew":{"from":"33703","to":"372","total":"37568","time":null},"info":{"from":"44953","to":"11623","total":"120960","gctime":"0.0008060","user":"0.00","sys":"0.00","real":"0.00"}},{"ParNew":{"from":"33780","to":"405","total":"37568","time":null},"info":{"from":"45031","to":"11656","total":"120960","gctime":"0.0007840","user":"0.00","sys":"0.00","real":"0.00"}},{"ParNew":{"from":"33813","to":"2915","total":"37568","time":null},"info":{"from":"45064","to":"14166","total":"120960","gctime":"0.0019150","user":"0.02","sys":"0.00","real":"0.00"}},{"ParNew":{"from":"36323","to":"4160","total":"37568","time":null},"info":{"from":"47574","to":"20235","total":"120960","gctime":"0.0078330","user":"0.05","sys":"0.00","real":"0.01"}}],"heap":{"par new generation ":{"total":"37568","used":"11920","eden space ":{"size":"33408","percent":"23"},"from space ":{"size":"4160","percent":"100"},"to   space ":{"size":"4160","percent":"0"}}},"stats":{"DefNew_count":0,"PSYoungGen_count":0,"PSOldGen_count":0,"PSPermGen_count":0}},"UseG1GC":{"gc_runs":[{"info":{"gctime":"0.0006540"}},{"info":{"gctime":"0.0005030"}},{"info":{"gctime":"0.0005510"}},{"info":{"gctime":"0.0007040"}},{"info":{"gctime":"0.0005180"}},{"info":{"gctime":"0.0006240"}},{"info":{"gctime":"0.0005260"}},{"info":{"gctime":"0.0004410"}},{"info":{"gctime":"0.0006700"}},{"info":{"gctime":"0.0004870"}},{"info":{"gctime":"0.0004640"}},{"info":{"gctime":"0.0007170"}},{"info":{"gctime":"0.0004120"}},{"info":{"gctime":"0.0005580"}},{"info":{"gctime":"0.0005290"}},{"info":{"gctime":"0.0007790"}},{"info":{"gctime":"0.0005600"}},{"info":{"gctime":"0.0006130"}},{"info":{"gctime":"0.0004990"}},{"info":{"gctime":"0.0004490"}},{"info":{"gctime":"0.0005870"}},{"info":{"gctime":"0.0004430"}},{"info":{"gctime":"0.0004870"}},{"info":{"gctime":"0.0004620"}},{"info":{"gctime":"0.0004470"}},{"info":{"gctime":"0.0006800"}},{"info":{"gctime":"0.0004690"}},{"info":{"gctime":"0.0005980"}},{"info":{"gctime":"0.0004650"}},{"info":{"gctime":"0.0004850"}},{"info":{"gctime":"0.0005300"}},{"info":{"gctime":"0.0007540"}},{"info":{"gctime":"0.0004990"}},{"info":{"gctime":"0.0006920"}},{"info":{"gctime":"0.0004450"}},{"info":{"gctime":"0.0005800"}},{"info":{"gctime":"0.0005910"}},{"info":{"gctime":"0.0008790"}}],"heap":{"first heap ":{"total":"69632","used":"24334"},"compacting perm gen ":{"total":"20480","used":"12901"}},"stats":{"DefNew_count":0,"PSYoungGen_count":0,"PSOldGen_count":0,"PSPermGen_count":0}},"UseParNewGC":{"gc_runs":[{"Tenured":{"from":"0","to":"3145","total":"83392","time":null},"Perm":{"from":"5076","to":"5076","total":"21248","time":null},"info":{"gctime":"0.0088970","from":"11089","to":"3145","total":"120896","user":"0.01","sys":"0.01","real":"0.01"}},{"Tenured":{"from":"3145","to":"3145","total":"83392","time":null},"Perm":{"from":"5076","to":"5076","total":"21248","time":null},"info":{"gctime":"0.0058320","from":"3145","to":"3145","total":"120960","user":"0.01","sys":"0.00","real":"0.01"}},{"ParNew":{"from":"33408","to":"4159","total":"37568","time":null},"info":{"from":"36553","to":"7389","total":"120960","gctime":"0.0013900","user":"0.01","sys":"0.00","real":"0.00"}},{"ParNew":{"from":"37567","to":"278","total":"37568","time":null},"info":{"from":"40797","to":"7445","total":"120960","gctime":"0.0009090","user":"0.01","sys":"0.00","real":"0.00"}},{"ParNew":{"from":"33686","to":"99","total":"37568","time":null},"info":{"from":"40853","to":"7266","total":"120960","gctime":"0.0006450","user":"0.01","sys":"0.00","real":"0.00"}},{"ParNew":{"from":"33507","to":"4158","total":"37568","time":null},"info":{"from":"40674","to":"11429","total":"120960","gctime":"0.0009610","user":"0.01","sys":"0.00","real":"0.00"}},{"ParNew":{"from":"37566","to":"290","total":"37568","time":null},"info":{"from":"44837","to":"11495","total":"120960","gctime":"0.0013470","user":"0.01","sys":"0.00","real":"0.00"}},{"ParNew":{"from":"33695","to":"303","total":"37568","time":null},"info":{"from":"44899","to":"11508","total":"120960","gctime":"0.0006470","user":"0.00","sys":"0.00","real":"0.00"}},{"ParNew":{"from":"33711","to":"375","total":"37568","time":null},"info":{"from":"44916","to":"11579","total":"120960","gctime":"0.0008760","user":"0.01","sys":"0.00","real":"0.01"}},{"ParNew":{"from":"33783","to":"387","total":"37568","time":null},"info":{"from":"44987","to":"11591","total":"120960","gctime":"0.0005010","user":"0.00","sys":"0.00","real":"0.00"}},{"ParNew":{"from":"33795","to":"4160","total":"37568","time":null},"info":{"from":"44999","to":"15620","total":"120960","gctime":"0.0021640","user":"0.01","sys":"0.00","real":"0.00"}},{"ParNew":{"from":"37568","to":"3791","total":"37568","time":null},"info":{"from":"49028","to":"18043","total":"120960","gctime":"0.0029860","user":"0.02","sys":"0.00","real":"0.00"}}],"heap":{"par new generation ":{"total":"37568","used":"7228","eden space ":{"size":"33408","percent":"10"},"from space ":{"size":"4160","percent":"91"},"to   space ":{"size":"4160","percent":"0"}},"tenured generation ":{"total":"83392","used":"14251"},"compacting perm gen ":{"total":"21248","used":"12905"}},"stats":{"DefNew_count":0,"PSYoungGen_count":0,"PSOldGen_count":0,"PSPermGen_count":0}},"UseParallelGC":{"gc_runs":[{"PSYoungGen":{"from":"10653","to":"3288","total":"36864","time":null},"info":{"from":"10653","to":"3296","total":"119808","gctime":"0.0023900","user":"0.01","sys":"0.00","real":"0.00"}},{"PSYoungGen":{"from":"3288","to":"0","total":"36864","time":null},"ParOldGen":{"from":"8","to":"3145","total":"82944","time":null},"PSPermGen":{"from":"5075","to":"5074","total":"21504","time":null},"info":{"gctime":"0.0108830","from":"3296","to":"3145","total":"119808","user":"0.04","sys":"0.00","real":"0.01"}},{"PSYoungGen":{"from":"0","to":"0","total":"36864","time":null},"info":{"from":"3145","to":"3145","total":"119808","gctime":"0.0003090","user":"0.00","sys":"0.00","real":"0.00"}},{"PSYoungGen":{"from":"0","to":"0","total":"36864","time":null},"ParOldGen":{"from":"3145","to":"3145","total":"82944","time":null},"PSPermGen":{"from":"5074","to":"5074","total":"21504","time":null},"info":{"gctime":"0.0042410","from":"3145","to":"3145","total":"119808","user":"0.01","sys":"0.01","real":"0.01"}},{"PSYoungGen":{"from":"31744","to":"4448","total":"36864","time":null},"info":{"from":"34889","to":"7593","total":"119808","gctime":"0.0012360","user":"0.01","sys":"0.00","real":"0.00"}},{"PSYoungGen":{"from":"36192","to":"4464","total":"36864","time":null},"info":{"from":"39337","to":"7609","total":"119808","gctime":"0.0009430","user":"0.00","sys":"0.01","real":"0.00"}},{"PSYoungGen":{"from":"36208","to":"4448","total":"36864","time":null},"info":{"from":"39353","to":"7593","total":"119808","gctime":"0.0012320","user":"0.01","sys":"0.00","real":"0.00"}},{"PSYoungGen":{"from":"36182","to":"4448","total":"36864","time":null},"info":{"from":"39327","to":"7593","total":"119808","gctime":"0.0012050","user":"0.01","sys":"0.00","real":"0.00"}},{"PSYoungGen":{"from":"36185","to":"4544","total":"36352","time":null},"info":{"from":"39330","to":"7689","total":"119296","gctime":"0.0012150","user":"0.01","sys":"0.00","real":"0.00"}},{"PSYoungGen":{"from":"35762","to":"4576","total":"37376","time":null},"info":{"from":"38907","to":"7721","total":"120320","gctime":"0.0012130","user":"0.00","sys":"0.00","real":"0.00"}},{"PSYoungGen":{"from":"35292","to":"4528","total":"34816","time":null},"info":{"from":"38438","to":"7769","total":"117760","gctime":"0.0014950","user":"0.01","sys":"0.00","real":"0.00"}},{"PSYoungGen":{"from":"34731","to":"464","total":"36864","time":null},"info":{"from":"37972","to":"7817","total":"119808","gctime":"0.0009420","user":"0.00","sys":"0.00","real":"0.00"}},{"PSYoungGen":{"from":"30160","to":"464","total":"29696","time":null},"info":{"from":"37513","to":"7897","total":"112640","gctime":"0.0007990","user":"0.00","sys":"0.00","real":"0.00"}},{"PSYoungGen":{"from":"29648","to":"6122","total":"36352","time":null},"info":{"from":"37081","to":"13691","total":"119296","gctime":"0.0034380","user":"0.03","sys":"0.00","real":"0.00"}},{"PSYoungGen":{"from":"34766","to":"1521","total":"29696","time":null},"info":{"from":"42335","to":"12646","total":"112640","gctime":"0.0031810","user":"0.02","sys":"0.00","real":"0.01"}}],"heap":{"PSYoungGen ":{"total":"29696","used":"4661","eden space ":{"size":"28160","percent":"11"},"from space ":{"size":"1536","percent":"99"},"to   space ":{"size":"8192","percent":"0"}},"ParOldGen ":{"total":"82944","used":"11124","object space ":{"size":"82944","percent":"13"}},"PSPermGen ":{"total":"21504","used":"12911","object space ":{"size":"21504","percent":"60"}}},"stats":{"DefNew_count":0,"PSYoungGen_count":15,"PSOldGen_count":0,"PSPermGen_count":2}},"UseParallelOldGC":{"gc_runs":[{"PSYoungGen":{"from":"10653","to":"3320","total":"36864","time":null},"info":{"from":"10653","to":"3328","total":"119808","gctime":"0.0023630","user":"0.01","sys":"0.01","real":"0.00"}},{"PSYoungGen":{"from":"3320","to":"0","total":"36864","time":null},"ParOldGen":{"from":"8","to":"3145","total":"82944","time":null},"PSPermGen":{"from":"5075","to":"5074","total":"21504","time":null},"info":{"gctime":"0.0115770","from":"3328","to":"3145","total":"119808","user":"0.04","sys":"0.00","real":"0.01"}},{"PSYoungGen":{"from":"0","to":"0","total":"36864","time":null},"info":{"from":"3145","to":"3145","total":"119808","gctime":"0.0002900","user":"0.00","sys":"0.00","real":"0.00"}},{"PSYoungGen":{"from":"0","to":"0","total":"36864","time":null},"ParOldGen":{"from":"3145","to":"3145","total":"82944","time":null},"PSPermGen":{"from":"5074","to":"5074","total":"21504","time":null},"info":{"gctime":"0.0039520","from":"3145","to":"3145","total":"119808","user":"0.02","sys":"0.00","real":"0.00"}},{"PSYoungGen":{"from":"31744","to":"4512","total":"36864","time":null},"info":{"from":"34889","to":"7657","total":"119808","gctime":"0.0017390","user":"0.00","sys":"0.00","real":"0.00"}},{"PSYoungGen":{"from":"36256","to":"4464","total":"36864","time":null},"info":{"from":"39401","to":"7609","total":"119808","gctime":"0.0011190","user":"0.00","sys":"0.00","real":"0.00"}},{"PSYoungGen":{"from":"36203","to":"4480","total":"36864","time":null},"info":{"from":"39348","to":"7625","total":"119808","gctime":"0.0012110","user":"0.00","sys":"0.00","real":"0.01"}},{"PSYoungGen":{"from":"36216","to":"4496","total":"36864","time":null},"info":{"from":"39361","to":"7641","total":"119808","gctime":"0.0011590","user":"0.01","sys":"0.00","real":"0.00"}},{"PSYoungGen":{"from":"36240","to":"4528","total":"36352","time":null},"info":{"from":"39385","to":"7673","total":"119296","gctime":"0.0014130","user":"0.01","sys":"0.00","real":"0.00"}},{"PSYoungGen":{"from":"35760","to":"4528","total":"37376","time":null},"info":{"from":"38905","to":"7673","total":"120320","gctime":"0.0013370","user":"0.01","sys":"0.00","real":"0.00"}},{"PSYoungGen":{"from":"35248","to":"4528","total":"34816","time":null},"info":{"from":"38393","to":"7777","total":"117760","gctime":"0.0014830","user":"0.01","sys":"0.00","real":"0.01"}},{"PSYoungGen":{"from":"34732","to":"432","total":"36864","time":null},"info":{"from":"37981","to":"7793","total":"119808","gctime":"0.0012750","user":"0.00","sys":"0.00","real":"0.00"}},{"PSYoungGen":{"from":"30113","to":"432","total":"29696","time":null},"info":{"from":"37474","to":"7865","total":"112640","gctime":"0.0008710","user":"0.00","sys":"0.00","real":"0.00"}},{"PSYoungGen":{"from":"29616","to":"6182","total":"36352","time":null},"info":{"from":"37049","to":"13744","total":"119296","gctime":"0.0034680","user":"0.02","sys":"0.00","real":"0.00"}},{"PSYoungGen":{"from":"34767","to":"1521","total":"29696","time":null},"info":{"from":"42328","to":"12634","total":"112640","gctime":"0.0027090","user":"0.02","sys":"0.00","real":"0.01"}}],"heap":{"PSYoungGen ":{"total":"29696","used":"4872","eden space ":{"size":"28160","percent":"11"},"from space ":{"size":"1536","percent":"99"},"to   space ":{"size":"8192","percent":"0"}},"ParOldGen ":{"total":"82944","used":"11112","object space ":{"size":"82944","percent":"13"}},"PSPermGen ":{"total":"21504","used":"12910","object space ":{"size":"21504","percent":"60"}}},"stats":{"DefNew_count":0,"PSYoungGen_count":15,"PSOldGen_count":0,"PSPermGen_count":2}},"UseSerialGC":{"gc_runs":[{"Tenured":{"from":"0","to":"3145","total":"83392","time":null},"Perm":{"from":"5075","to":"5075","total":"21248","time":null},"info":{"gctime":"0.0088350","from":"10422","to":"3145","total":"120896","user":"0.01","sys":"0.00","real":"0.01"}},{"Tenured":{"from":"3145","to":"3145","total":"83392","time":null},"Perm":{"from":"5075","to":"5075","total":"21248","time":null},"info":{"gctime":"0.0056250","from":"3145","to":"3145","total":"120960","user":"0.00","sys":"0.00","real":"0.01"}},{"DefNew":{"from":"33408","to":"4160","total":"37568","time":null},"info":{"from":"36553","to":"7363","total":"120960","gctime":"0.0020340","user":"0.00","sys":"0.01","real":"0.00"}},{"DefNew":{"from":"37568","to":"254","total":"37568","time":null},"info":{"from":"40771","to":"7428","total":"120960","gctime":"0.0016550","user":"0.00","sys":"0.00","real":"0.00"}},{"DefNew":{"from":"33662","to":"257","total":"37568","time":null},"info":{"from":"40836","to":"7431","total":"120960","gctime":"0.0004350","user":"0.00","sys":"0.00","real":"0.00"}},{"DefNew":{"from":"33656","to":"4159","total":"37568","time":null},"info":{"from":"40831","to":"11442","total":"120960","gctime":"0.0015820","user":"0.00","sys":"0.00","real":"0.00"}},{"DefNew":{"from":"37557","to":"240","total":"37568","time":null},"info":{"from":"44839","to":"11486","total":"120960","gctime":"0.0016080","user":"0.00","sys":"0.00","real":"0.00"}},{"DefNew":{"from":"33648","to":"259","total":"37568","time":null},"info":{"from":"44894","to":"11506","total":"120960","gctime":"0.0003950","user":"0.00","sys":"0.00","real":"0.00"}},{"DefNew":{"from":"33667","to":"310","total":"37568","time":null},"info":{"from":"44914","to":"11557","total":"120960","gctime":"0.0004460","user":"0.00","sys":"0.00","real":"0.00"}},{"DefNew":{"from":"33718","to":"338","total":"37568","time":null},"info":{"from":"44965","to":"11584","total":"120960","gctime":"0.0004430","user":"0.00","sys":"0.00","real":"0.00"}},{"DefNew":{"from":"33746","to":"2775","total":"37568","time":null},"info":{"from":"44992","to":"14022","total":"120960","gctime":"0.0041340","user":"0.01","sys":"0.00","real":"0.00"}},{"DefNew":{"from":"36174","to":"4159","total":"37568","time":null},"info":{"from":"47420","to":"19948","total":"120960","gctime":"0.0093190","user":"0.01","sys":"0.00","real":"0.01"}}],"heap":{"def new generation ":{"total":"37568","used":"12595","eden space ":{"size":"33408","percent":"25"},"from space ":{"size":"4160","percent":"99"},"to   space ":{"size":"4160","percent":"0"}},"tenured generation ":{"total":"83392","used":"15788"},"compacting perm gen ":{"total":"21248","used":"12913"}},"stats":{"DefNew_count":10,"PSYoungGen_count":0,"PSOldGen_count":0,"PSPermGen_count":0}}}